poremks/__init__.py
poremks/__version__.py
poremks/correlations.py
poremks/grid_generator.py
poremks/helpers.py
poremks/porosity.py
poremks-1.0.7.dist-info/METADATA
poremks-1.0.7.dist-info/RECORD
poremks-1.0.7.dist-info/WHEEL
poremks-1.0.7.dist-info/top_level.txt
