Metadata-Version: 2.1
Name: poremks
Version: 1.0.7
Summary: for analytics on nanoporous molecular structures
Home-page: https://auag92.github.io
Author: Apaar Shanker
Author-email: apaar92@gmail.com
License: MIT
Platform: UNKNOWN
Classifier: License :: OSI Approved :: MIT License
Classifier: Programming Language :: Python
Classifier: Programming Language :: Python :: 3
Classifier: Programming Language :: Python :: 3.6
Classifier: Programming Language :: Python :: Implementation :: CPython
Classifier: Programming Language :: Python :: Implementation :: PyPy
Requires-Python: >=3.6.0
Provides-Extra: for fast euclidean distance transform
Provides-Extra: for fast FFT
Requires-Dist: numpy
Requires-Dist: scipy
Requires-Dist: scikit-image
Requires-Dist: toolz
Requires-Dist: ase
Requires-Dist: numba
Provides-Extra: for fast FFT
Requires-Dist: pytorch; extra == 'for fast FFT'
Provides-Extra: for fast euclidean distance transform
Requires-Dist: edt; extra == 'for fast euclidean distance transform'
